microflex/__init__.py
microflex/analysis/__init__.py
microflex/analysis/diversity.py
microflex/cli/__init__.py
microflex/cli/main.py
microflex/core/__init__.py
microflex/core/base.py
microflex/core/config.py
microflex/core/exceptions.py
microflex/core/interfaces.py
microflex/core/types.py
microflex/functional/__init__.py
microflex/io/__init__.py
microflex/io/ab1_reader.py
microflex/io/biom_reader.py
microflex/io/fasta_reader.py
microflex/io/fastq_reader.py
microflex/io/format_detector.py
microflex/io/qza_reader.py
microflex/io/sequence_writer.py
microflex/io/taxonomy_writer.py
microflex/preprocess/__init__.py
microflex/preprocess/quality_filter.py
microflex/taxonomy/__init__.py
microflex/taxonomy/blast_classifier.py
microflex/taxonomy/mock_classifier.py
microflex/utils/__init__.py
microflex/visualization/__init__.py
microflex-0.1.0.dist-info/licenses/LICENSE
microflex-0.1.0.dist-info/METADATA
microflex-0.1.0.dist-info/WHEEL
microflex-0.1.0.dist-info/entry_points.txt
microflex-0.1.0.dist-info/top_level.txt
microflex-0.1.0.dist-info/RECORD
