Metadata-Version: 2.4
Name: microflex
Version: 0.1.0
Summary: Cross-platform Python toolkit for microbiome analysis using multiple sequencing technologies
Author-email: Ata Umut Özsoy <ataumut7@gmail.com>
Maintainer-email: Ata Umut Özsoy <ataumut7@gmail.com>
License-Expression: MIT
Project-URL: Homepage, https://github.com/ataozsoysoy/microflex
Project-URL: Documentation, https://microflex.readthedocs.io
Project-URL: Repository, https://github.com/ataozsoysoy/microflex
Project-URL: Bug Tracker, https://github.com/ataozsoysoy/microflex/issues
Keywords: microbiome,bioinformatics,sequencing,NGS,nanopore,sanger
Classifier: Development Status :: 3 - Alpha
Classifier: Intended Audience :: Science/Research
Classifier: Operating System :: OS Independent
Classifier: Programming Language :: Python :: 3
Classifier: Programming Language :: Python :: 3.9
Classifier: Programming Language :: Python :: 3.10
Classifier: Programming Language :: Python :: 3.11
Classifier: Programming Language :: Python :: 3.12
Classifier: Topic :: Scientific/Engineering :: Bio-Informatics
Requires-Python: >=3.9
License-File: LICENSE
Requires-Dist: biopython>=1.81
Requires-Dist: pandas>=2.0.0
Requires-Dist: numpy>=1.24.0
Requires-Dist: scipy>=1.11.0
Requires-Dist: matplotlib>=3.7.0
Requires-Dist: seaborn>=0.12.0
Requires-Dist: plotly>=5.15.0
Requires-Dist: scikit-learn>=1.3.0
Requires-Dist: click>=8.1.0
Requires-Dist: pydantic>=2.0.0
Requires-Dist: typing-extensions>=4.5.0
Provides-Extra: dev
Requires-Dist: pytest>=7.4.0; extra == "dev"
Requires-Dist: pytest-cov>=4.1.0; extra == "dev"
Requires-Dist: black>=23.7.0; extra == "dev"
Requires-Dist: isort>=5.12.0; extra == "dev"
Requires-Dist: flake8>=6.0.0; extra == "dev"
Requires-Dist: mypy>=1.5.0; extra == "dev"
Requires-Dist: pre-commit>=3.3.0; extra == "dev"
Provides-Extra: web
Requires-Dist: dash>=2.14.0; extra == "web"
Requires-Dist: dash-bootstrap-components>=1.4.0; extra == "web"
Provides-Extra: docs
Requires-Dist: sphinx>=7.1.0; extra == "docs"
Requires-Dist: sphinx-rtd-theme>=1.3.0; extra == "docs"
Requires-Dist: myst-parser>=2.0.0; extra == "docs"
Dynamic: license-file
